setup.py
gauss_binom_probability/Binomialdistribution.py
gauss_binom_probability/Gaussiandistribution.py
gauss_binom_probability/Generaldistribution.py
gauss_binom_probability/__init__.py
gauss_binom_probability.egg-info/PKG-INFO
gauss_binom_probability.egg-info/SOURCES.txt
gauss_binom_probability.egg-info/dependency_links.txt
gauss_binom_probability.egg-info/not-zip-safe
gauss_binom_probability.egg-info/top_level.txt