Metadata-Version: 1.0
Name: gauss-binom-probability
Version: 0.1
Summary: Gaussian and Binomial distributions
Home-page: UNKNOWN
Author: Oluchi Obi-Alago
Author-email: ejindu.oluchukwu@gmail.com
License: UNKNOWN
Platform: UNKNOWN
